bombhtml/__init__.py
bombhtml/bomb.py
bombhtml-0.4.5.dist-info/licenses/LICENSE_GPL3
bombhtml-0.4.5.dist-info/licenses/LICENSE_MIT
bombhtml-0.4.5.dist-info/METADATA
bombhtml-0.4.5.dist-info/WHEEL
bombhtml-0.4.5.dist-info/top_level.txt
bombhtml-0.4.5.dist-info/RECORD
