Metadata-Version: 2.4
Name: bombhtml
Version: 0.4.5
Summary: simple html/css templating / static site generator system written in python
Author-email: sophie <itsme@itssophi.ee>
License-Expression: MIT AND GPL-3.0-or-later
Project-URL: Repository, https://codeberg.org/emailbomb/bombhtml
Project-URL: Documentation, https://codeberg.org/emailbomb/bombhtml/src/branch/main/CONFIGURING.md
Project-URL: Issues, https://codeberg.org/emailbomb/bombhtml/issues
Project-URL: Changelog, https://codeberg.org/emailbomb/bombhtml/src/branch/main/CHANGELOG.md
Keywords: html,html/css,templating,static site generator
Classifier: Development Status :: 3 - Alpha
Classifier: Intended Audience :: Developers
Classifier: Natural Language :: English
Classifier: Programming Language :: Python :: 3
Classifier: Programming Language :: Python :: 3.11
Requires-Python: >=3.11
License-File: LICENSE_MIT
License-File: LICENSE_GPL3
Dynamic: license-file
